passhash/__init__.py
passhash/_version.py
passhash/algorithms.yml
passhash/passhash.py
passhash-1.0.1.dist-info/LICENSE
passhash-1.0.1.dist-info/METADATA
passhash-1.0.1.dist-info/WHEEL
passhash-1.0.1.dist-info/entry_points.txt
passhash-1.0.1.dist-info/top_level.txt
passhash-1.0.1.dist-info/RECORD
