Metadata-Version: 2.1
Name: passhash
Version: 1.0.1
Summary: Generate password hashes based on various standards.
Author-email: ReK42 <ReK42@users.noreply.github.com>
Maintainer-email: ReK42 <ReK42@users.noreply.github.com>
License: GNU GENERAL PUBLIC LICENSE
Project-URL: Repository, https://github.com/ReK42/passhash
Project-URL: Issues, https://github.com/ReK42/passhash/issues
Keywords: bandcamp,music
Classifier: Development Status :: 4 - Beta
Classifier: Environment :: Console
Classifier: Intended Audience :: Information Technology
Classifier: Intended Audience :: System Administrators
Classifier: Intended Audience :: Telecommunications Industry
Classifier: License :: OSI Approved :: GNU General Public License v3 (GPLv3)
Classifier: Natural Language :: English
Classifier: Operating System :: OS Independent
Classifier: Programming Language :: Python
Classifier: Programming Language :: Python :: 3
Classifier: Programming Language :: Python :: 3 :: Only
Classifier: Programming Language :: Python :: 3.10
Classifier: Programming Language :: Python :: 3.11
Classifier: Topic :: Security
Classifier: Topic :: Security :: Cryptography
Classifier: Topic :: System :: Networking
Classifier: Topic :: System :: Systems Administration
Classifier: Topic :: System :: Systems Administration :: Authentication/Directory
Classifier: Topic :: System :: Systems Administration :: Authentication/Directory :: LDAP
Classifier: Topic :: Utilities
Classifier: Typing :: Typed
Requires-Python: >=3.10
License-File: LICENSE
Requires-Dist: PyYAML ==6.0.1
Requires-Dist: rich ==13.5.2
Requires-Dist: passlib ==1.7.4
Requires-Dist: bcrypt ==4.0.1
Provides-Extra: build
Requires-Dist: setuptools ==68.2.0 ; extra == 'build'
Requires-Dist: setuptools-scm ==7.1.0 ; extra == 'build'
Requires-Dist: build ==1.0.3 ; extra == 'build'
Requires-Dist: twine ==4.0.2 ; extra == 'build'
Provides-Extra: tests
Requires-Dist: black ==23.9.1 ; extra == 'tests'
Requires-Dist: mypy ==1.5.1 ; extra == 'tests'
Requires-Dist: ruff ==0.0.288 ; extra == 'tests'
Requires-Dist: types-PyYAML ==6.0.12.11 ; extra == 'tests'
Requires-Dist: types-passlib ==1.7.7.13 ; extra == 'tests'
